api/__init__.py
api/ingest/__init__.py
api/ingest/app_factory.py
api/ingest/main.py
api/ingest/routes.py
api/ingest/sinks/__init__.py
api/ingest/sinks/base_sink.py
api/ingest/sinks/postgres_async.py
api/ingest/sinks/sqlite_async.py
api/viewer/__init__.py
api/viewer/app_factory.py
api/viewer/main.py
api/viewer/readers/__init__.py
api/viewer/readers/archived/memory_reader.py
api/viewer/readers/archived/memory_store.py
api/viewer/readers/base_reader.py
api/viewer/readers/postgres_reader.py
api/viewer/readers/sqlite_reader.py
api/viewer/routes.py
dashboard/__init__.py
dashboard/index.html
producers/__init__.py
producers/archive/log_tail.py
producers/listener/__init__.py
producers/listener/listener.py
producers/log_producer/__init__.py
producers/log_producer/log_tails.py
producers/metrics/__init__.py
producers/metrics/metric_scraper.py
shared/__init__.py
shared/helpers/__init__.py
shared/helpers/cli.py
shared/helpers/config_loader.py
shared/helpers/ensure_db_schema.py
shared/helpers/kill_backend.py
shared/helpers/log_line_datetime_patterns.py
shared/helpers/log_line_parser.py
shared/helpers/logger.py
shared/helpers/setup_wizard.py
shared/helpers/sql_definitions.py
shared/sinks/__init__.py
shared/sinks/archived/memory.py
shared/sinks/archived/memory_sqlite.py
shared/sinks/archived/postgres.py
shared/sinks/base.py
shared/sinks/http.py
shared/sinks/loki.py
shared/sinks/sqlite.py
robotframework_realtimeresults-0.4.2.dist-info/LICENSE
robotframework_realtimeresults-0.4.2.dist-info/METADATA
robotframework_realtimeresults-0.4.2.dist-info/WHEEL
robotframework_realtimeresults-0.4.2.dist-info/entry_points.txt
robotframework_realtimeresults-0.4.2.dist-info/RECORD
